<?xml version="1.0" encoding="utf-8"?>
<craftDefinition>
	<parent name="Grilling" title="What would you like to make?" selectresource="true">
		<parent name="Breakfast" itemID="0x1E1F" hue="0x22A" title="What do you want to make?">
			<child name="pancakes" typename="Pancakes" hue="0x22A" />
			<child name="waffles" typename="Waffles" hue="0x1C7" />
			<child name="fried eggs" typename="FriedEggs" />
			<child name="bacon" typename="Bacon" />
		</parent>
		<parent name="Barbecue" itemID="0x9F2" title="What do you want to make?">
			<child name="ribs" typename="Ribs" />
			<child name="cooked bird" typename="CookedBird" />
			<child name="chicken leg" typename="ChickenLeg" />
			<child name="fish steak" typename="FishSteak" />
			<child name="lamb leg" typename="LambLeg" />
			<child name="smoked ribs" typename="SmokedRibs" hue="0x340" />
			<child name="spiced ribs" typename="SpicedRibs" hue="0x2F4" />
			<child name="energetic ribs" typename="EnergeticRibs" hue="0xED" />
			<child name="smoked fish steak" typename="SmokedFishSteak" hue="0x340" />
			<child name="spiced fish steak" typename="SpicedFishSteak" hue="0x2F4" />
			<child name="energetic fish steak" typename="EnergeticFishSteak" hue="0xED" />
			<child name="steak" typename="CookedSteak" />
			<child name="ham slices" typename="HamSlices" />
			<child name="roast ham" typename="RoastHam" />
		</parent>
		<parent name="Dinners" itemID="0x9DB" title="What do you want to make?">
			<child name="beef barbecue ribs" typename="BeefBBQRibs" />
			<child name="beef and broccoli" typename="BeefBroccoli" />
			<child name="cho cho beef" typename="ChoChoBeef" />
			<child name="beef and snow peas" typename="BeefSnowpeas" />
			<child name="hamburger" typename="Hamburger" />
			<child name="beef lo mein" typename="BeefLoMein" />
			<child name="beef stirfry" typename="BeefStirfry" />
			<child name="chicken stirfry" typename="ChickenStirfry" />
			<child name="moo shu pork" typename="MooShuPork" />
			<child name="mo po tofu" typename="MoPoTofu" />
			<child name="pork stirfry" typename="PorkStirfry" />
			<child name="sweet and sour chicken" typename="SweetSourChicken" />
			<child name="sweet and sour pork" typename="SweetSourPork" />
			<child name="bacon and eggs" typename="BaconAndEgg" />
		</parent>
		<parent name="Other Food" itemID="0x98C" hue="0x1C8" title="What do you want to make?">
			<child name="garlic bread" typename="GarlicBread" hue="0x1C8" />
			<child name="grilled ham" typename="GrilledHam" hue="0x33D" />
			<child name="sausage" typename="Sausage" />
			<child name="hotwings" typename="Hotwings" hue="0x21A" />
			<child name="potato fries" typename="PotatoFries" />
			<child name="taco" typename="Taco" hue="0x465" />
		</parent>
	</parent>
</craftDefinition>